<declarations><declaration>
		<dateDepot>04/01/2022 15:17:54</dateDepot>
		<uuid>86996c80-a4d7-44d6-83ec-29d7482ee44b</uuid>
		<origine>ADEL</origine>
		<complete>true</complete>
		<attachedFiles>
			<attachedFiles>
				<fileName>VUE_PDF_DU_RECEPISSE_DU_DEPOT_XML</fileName>
				<serverFileName/>
				<base64EncodedContent/>
			</attachedFiles>
		</attachedFiles>
		<declarationVersion>20171221</declarationVersion>
		<activConsultantDto>
			<items/>
			<neant>true</neant>
		</activConsultantDto>
		<activProfCinqDerniereDto>
			<items>
				<items>
					<motif>
						<id>CREATION</id>
						<label/>
					</motif>
					<commentaire/>
					<description>Conseiller technique du Directeur G&#233;n&#233;ral des Services</description>
					<employeur>Conseil d&#233;partemental de l'Aisne</employeur>
					<remuneration>
						<brutNet>Net</brutNet>
						<montant>
							<montant>
								<annee>2016</annee>
								<montant>46&#8239;200</montant>
							</montant>
							<montant>
								<annee>2017</annee>
								<montant>63&#8239;823</montant>
							</montant>
							<montant>
								<annee>2018</annee>
								<montant>63&#8239;909</montant>
							</montant>
							<montant>
								<annee>2019</annee>
								<montant>48&#8239;245</montant>
							</montant>
							<montant>
								<annee>2020</annee>
								<montant>48&#8239;629</montant>
							</montant>
							<montant>
								<annee>2021</annee>
								<montant>28&#8239;133</montant>
							</montant>
						</montant>
					</remuneration>
					<dateDebut>07/2016</dateDebut>
					<dateFin>07/2021</dateFin>
				</items>
			</items>
			<neant>false</neant>
		</activProfCinqDerniereDto>
		<activProfConjointDto>
			<items>
				<items>
					<motif>
						<id>CREATION</id>
						<label/>
					</motif>
					<commentaire/>
					<nomConjoint>
            [Donn&#233;es non publi&#233;es]
        </nomConjoint>
					<employeurConjoint>Greta de l'Aisne</employeurConjoint>
					<activiteProf>Formateur en formation continue</activiteProf>
				</items>
			</items>
			<neant>false</neant>
		</activProfConjointDto>
		<fonctionBenevoleDto>
			<items/>
			<neant>true</neant>
		</fonctionBenevoleDto>
		<mandatElectifDto>
			<items>
				<items>
					<motif>
						<id>CREATION</id>
						<label/>
					</motif>
					<commentaire/>
					<descriptionMandat>Maire-adjoint, commune d'Aulnois-sous-Laon</descriptionMandat>
					<remuneration>
						<brutNet>Net</brutNet>
						<montant>
							<montant>
								<annee>2016</annee>
								<montant>5&#8239;832</montant>
							</montant>
							<montant>
								<annee>2017</annee>
								<montant>5&#8239;827</montant>
							</montant>
							<montant>
								<annee>2018</annee>
								<montant>5&#8239;719</montant>
							</montant>
							<montant>
								<annee>2019</annee>
								<montant>3&#8239;606</montant>
							</montant>
							<montant>
								<annee>2020</annee>
								<montant>4&#8239;253</montant>
							</montant>
							<montant>
								<annee>2021</annee>
								<montant>2&#8239;202</montant>
							</montant>
						</montant>
					</remuneration>
					<dateDebut>07/2016</dateDebut>
					<dateFin>07/2021</dateFin>
				</items>
				<items>
					<motif>
						<id>CREATION</id>
						<label/>
					</motif>
					<commentaire/>
					<descriptionMandat>Vice-pr&#233;sident du Conseil r&#233;gional des Hauts-de-France</descriptionMandat>
					<remuneration>
						<brutNet>Net</brutNet>
						<montant>
							<montant>
								<annee>2016</annee>
								<montant>42&#8239;243</montant>
							</montant>
							<montant>
								<annee>2017</annee>
								<montant>39&#8239;422</montant>
							</montant>
							<montant>
								<annee>2018</annee>
								<montant>39&#8239;000</montant>
							</montant>
							<montant>
								<annee>2019</annee>
								<montant>25&#8239;764</montant>
							</montant>
							<montant>
								<annee>2020</annee>
								<montant>23&#8239;812</montant>
							</montant>
							<montant>
								<annee>2021</annee>
								<montant>14&#8239;383</montant>
							</montant>
						</montant>
					</remuneration>
					<dateDebut>07/2016</dateDebut>
					<dateFin>07/2021</dateFin>
				</items>
			</items>
			<neant>false</neant>
		</mandatElectifDto>
		<participationDirigeantDto>
			<items>
				<items>
					<motif>
						<id>CREATION</id>
						<label/>
					</motif>
					<commentaire>Membre du Conseil d'administration, d&#233;l&#233;gu&#233; de ma commune puis &#233;lu d&#233;l&#233;gu&#233; de mon canton. Fonction exerc&#233;e jusqu'en mars 2020</commentaire>
					<nomSociete>USEDA</nomSociete>
					<activite>Syndicat d&#233;partemental d'&#233;lectricit&#233;</activite>
					<remuneration>
						<brutNet>Net</brutNet>
						<montant>
							<montant>
								<annee>2015</annee>
								<montant>0</montant>
							</montant>
							<montant>
								<annee>2016</annee>
								<montant>0</montant>
							</montant>
							<montant>
								<annee>2017</annee>
								<montant>0</montant>
							</montant>
							<montant>
								<annee>2018</annee>
								<montant>0</montant>
							</montant>
							<montant>
								<annee>2019</annee>
								<montant>0</montant>
							</montant>
							<montant>
								<annee>2020</annee>
								<montant>0</montant>
							</montant>
						</montant>
					</remuneration>
					<dateDebut>03/2015</dateDebut>
					<dateFin>03/2020</dateFin>
				</items>
				<items>
					<motif>
						<id>CREATION</id>
						<label/>
					</motif>
					<commentaire/>
					<nomSociete>Communaut&#233; d'agglom&#233;ration de Laon</nomSociete>
					<activite>Conseiller communautaire repr&#233;sentant la commune d'Aulnois sous Laon</activite>
					<remuneration>
						<brutNet>Net</brutNet>
						<montant>
							<montant>
								<annee>2016</annee>
								<montant>0</montant>
							</montant>
							<montant>
								<annee>2017</annee>
								<montant>0</montant>
							</montant>
							<montant>
								<annee>2018</annee>
								<montant>0</montant>
							</montant>
							<montant>
								<annee>2019</annee>
								<montant>0</montant>
							</montant>
							<montant>
								<annee>2020</annee>
								<montant>0</montant>
							</montant>
							<montant>
								<annee>2021</annee>
								<montant>0</montant>
							</montant>
						</montant>
					</remuneration>
					<dateDebut>07/2016</dateDebut>
					<dateFin>07/2021</dateFin>
				</items>
				<items>
					<motif>
						<id>CREATION</id>
						<label/>
					</motif>
					<commentaire/>
					<nomSociete>Maison de l'Emploi et de la Formation du Laonnois</nomSociete>
					<activite>Vice pr&#233;sident de l'association pour la promotion de l'emploi local</activite>
					<remuneration>
						<brutNet>Net</brutNet>
						<montant>
							<montant>
								<annee>2015</annee>
								<montant>0</montant>
							</montant>
							<montant>
								<annee>2016</annee>
								<montant>0</montant>
							</montant>
							<montant>
								<annee>2017</annee>
								<montant>0</montant>
							</montant>
							<montant>
								<annee>2018</annee>
								<montant>0</montant>
							</montant>
							<montant>
								<annee>2019</annee>
								<montant>0</montant>
							</montant>
							<montant>
								<annee>2020</annee>
								<montant>0</montant>
							</montant>
						</montant>
					</remuneration>
					<dateDebut>03/2015</dateDebut>
					<dateFin>03/2020</dateFin>
				</items>
				<items>
					<motif>
						<id>CREATION</id>
						<label/>
					</motif>
					<commentaire/>
					<nomSociete>Nord Pas-de-Calais num&#233;rique</nomSociete>
					<activite>Pr&#233;sident du syndicat mixte</activite>
					<remuneration>
						<brutNet>Net</brutNet>
						<montant>
							<montant>
								<annee>2016</annee>
								<montant>7&#8239;551</montant>
							</montant>
							<montant>
								<annee>2017</annee>
								<montant>7&#8239;856</montant>
							</montant>
							<montant>
								<annee>2018</annee>
								<montant>7&#8239;780</montant>
							</montant>
							<montant>
								<annee>2019</annee>
								<montant>5&#8239;159</montant>
							</montant>
							<montant>
								<annee>2020</annee>
								<montant>5&#8239;086</montant>
							</montant>
							<montant>
								<annee>2021</annee>
								<montant>2&#8239;119</montant>
							</montant>
						</montant>
					</remuneration>
					<dateDebut>07/2016</dateDebut>
					<dateFin>07/2021</dateFin>
				</items>
				<items>
					<motif>
						<id>CREATION</id>
						<label/>
					</motif>
					<commentaire/>
					<nomSociete>Syndicat Mixte des A&#233;roports de Lille et Merville</nomSociete>
					<activite>Pr&#233;sident du syndicat mixte</activite>
					<remuneration>
						<brutNet>Net</brutNet>
						<montant>
							<montant>
								<annee>2016</annee>
								<montant>0</montant>
							</montant>
							<montant>
								<annee>2017</annee>
								<montant>0</montant>
							</montant>
							<montant>
								<annee>2018</annee>
								<montant>0</montant>
							</montant>
							<montant>
								<annee>2019</annee>
								<montant>0</montant>
							</montant>
							<montant>
								<annee>2020</annee>
								<montant>0</montant>
							</montant>
							<montant>
								<annee>2021</annee>
								<montant>0</montant>
							</montant>
						</montant>
					</remuneration>
					<dateDebut>07/2016</dateDebut>
					<dateFin>07/2021</dateFin>
				</items>
				<items>
					<motif>
						<id>CREATION</id>
						<label/>
					</motif>
					<commentaire>Administrateur non r&#233;mun&#233;r&#233;</commentaire>
					<nomSociete>RTA</nomSociete>
					<activite>R&#233;gie r&#233;gionale des transports de l'Aisne</activite>
					<remuneration>
						<brutNet>Net</brutNet>
						<montant>
							<montant>
								<annee>2021</annee>
								<montant>0</montant>
							</montant>
							<montant>
								<annee>2022</annee>
								<montant>0</montant>
							</montant>
						</montant>
					</remuneration>
					<dateDebut>07/2021</dateDebut>
					<dateFin/>
				</items>
				<items>
					<motif>
						<id>CREATION</id>
						<label/>
					</motif>
					<commentaire>Administrateur b&#233;n&#233;vole</commentaire>
					<nomSociete>SAFER des Hauts-de-France</nomSociete>
					<activite>Soci&#233;t&#233; d'am&#233;nagement foncier et d'&#233;tablissement rural</activite>
					<remuneration>
						<brutNet>Net</brutNet>
						<montant>
							<montant>
								<annee>2021</annee>
								<montant>0</montant>
							</montant>
							<montant>
								<annee>2022</annee>
								<montant>0</montant>
							</montant>
						</montant>
					</remuneration>
					<dateDebut>10/2021</dateDebut>
					<dateFin/>
				</items>
			</items>
			<neant>false</neant>
		</participationDirigeantDto>
		<participationFinanciereDto>
			<items/>
			<neant>true</neant>
		</participationFinanciereDto>
		<activCollaborateursDto>
			<items/>
			<neant>false</neant>
		</activCollaborateursDto>
		<observationInteretDto>
			<items>
				<items>
					<motif>
						<id>CREATION</id>
						<label/>
					</motif>
					<commentaire/>
					<contenu>
        [Donn&#233;es non publi&#233;es]
    </contenu>
				</items>
			</items>
			<neant>false</neant>
		</observationInteretDto>
		<general>
			<typeDeclaration>
				<id>DI</id>
				<label>D&#233;claration d'int&#233;r&#234;ts modificative</label>
			</typeDeclaration>
			<mandat>
				<label>Elu local ou membre d&#8217;un &#233;tablissement public de coop&#233;ration intercommunale</label>
			</mandat>
			<qualiteMandat>
				<typeMandat>Elu r&#233;gional</typeMandat>
				<codCategorieMandat>LOC</codCategorieMandat>
				<nomCategorieMandat>Elu local ou membre d&#8217;EPCI</nomCategorieMandat>
				<codTypeMandatFichier>cr</codTypeMandatFichier>
				<labelTypeMandat>Elu r&#233;gional</labelTypeMandat>
				<labelOrgane>R&#233;gion</labelOrgane>
				<codeListeOrgane>REG</codeListeOrgane>
			</qualiteMandat>
			<organe>
				<codeOrgane>32</codeOrgane>
				<codeListeOrgane>REG</codeListeOrgane>
				<nomListeOrgane>R&#233;gions</nomListeOrgane>
				<labelOrgane>Hauts-de-France (32)</labelOrgane>
				<labelDeclaration/>
				<organeParent/>
			</organe>
			<qualiteDeclarant>vice-pr&#233;sident</qualiteDeclarant>
			<qualiteDeclarantForPDF>Elu r&#233;gional/Hauts-de-France (32)/vice-pr&#233;sident</qualiteDeclarantForPDF>
			<dateDebutMandat>06/07/2021</dateDebutMandat>
			<dateFinMandat/>
			<dateDernDeclar/>
			<regimeMatrimonial/>
			<regimeMatrimonialComments/>
			<nomSociete/>
			<nomSocieteMere/>
			<chiffreAffaire/>
			<nbLogements/>
			<declarationModificative>true</declarationModificative>
			<declarant>
				<civilite>M.</civilite>
				<nom>COULON</nom>
				<prenom>Christophe</prenom>
				<email>
            [Donn&#233;es non publi&#233;es]
        </email>
				<dateNaissance>11/05/1973</dateNaissance>
				<pieceIdentite/>
				<telephoneDec>
            [Donn&#233;es non publi&#233;es]
        </telephoneDec>
				<adresseDec>
					<voie>
            [Donn&#233;es non publi&#233;es]
        </voie>
					<complement>
            [Donn&#233;es non publi&#233;es]
        </complement>
					<codePostal>
            [Donn&#233;es non publi&#233;es]
        </codePostal>
					<ville>
            [Donn&#233;es non publi&#233;es]
        </ville>
					<pays>
            [Donn&#233;es non publi&#233;es]
        </pays>
				</adresseDec>
			</declarant>
		</general>
	</declaration>
	</declarations>
