<declarations><declaration>
		<dateDepot>15/02/2021 10:28:07</dateDepot>
		<uuid>e51754f2-b3a0-410a-b0a2-634dede6a81f</uuid>
		<origine>ADEL</origine>
		<complete>true</complete>
		<attachedFiles>
			<attachedFiles>
				<fileName>VUE_PDF_DU_RECEPISSE_DU_DEPOT_XML</fileName>
				<serverFileName/>
				<base64EncodedContent/>
			</attachedFiles>
		</attachedFiles>
		<declarationVersion>20171221</declarationVersion>
		<activConsultantDto>
			<items/>
			<neant>true</neant>
		</activConsultantDto>
		<activProfCinqDerniereDto>
			<items>
				<items>
					<motif>
						<id>CREATION</id>
						<label/>
					</motif>
					<commentaire>Fonction de vice pr&#233;sident &#224; compter de juillet 2020 &#224;ce jour</commentaire>
					<description>vice pr&#233;sident</description>
					<employeur>Agglom&#233;ration Lens/Li&#233;vin</employeur>
					<remuneration>
						<brutNet>Net</brutNet>
						<montant>
							<montant>
								<annee>2020</annee>
								<montant>9&#160;382</montant>
							</montant>
							<montant>
								<annee>2021</annee>
								<montant>1&#160;571</montant>
							</montant>
						</montant>
					</remuneration>
					<dateDebut>07/2020</dateDebut>
					<dateFin>01/2021</dateFin>
				</items>
			</items>
			<neant>false</neant>
		</activProfCinqDerniereDto>
		<activProfConjointDto>
			<items>
				<items>
					<motif>
						<id>CREATION</id>
						<label/>
					</motif>
					<commentaire/>
					<nomConjoint>
            [Donn&#233;es non publi&#233;es]
        </nomConjoint>
					<employeurConjoint>Retrait&#233;e</employeurConjoint>
					<activiteProf>Secr&#233;taire</activiteProf>
				</items>
			</items>
			<neant>false</neant>
		</activProfConjointDto>
		<fonctionBenevoleDto>
			<items/>
			<neant>true</neant>
		</fonctionBenevoleDto>
		<mandatElectifDto>
			<items>
				<items>
					<motif>
						<id>CREATION</id>
						<label/>
					</motif>
					<commentaire>R&#233;mun&#233;ration de 2020correspond &#224; l'ann&#233;e enti&#232;reet 2021 correspond au moisde janvier</commentaire>
					<descriptionMandat>Maire</descriptionMandat>
					<remuneration>
						<brutNet>Net</brutNet>
						<montant>
							<montant>
								<annee>2020</annee>
								<montant>10&#160;953</montant>
							</montant>
							<montant>
								<annee>2021</annee>
								<montant>785</montant>
							</montant>
						</montant>
					</remuneration>
					<dateDebut>07/2020</dateDebut>
					<dateFin>01/2021</dateFin>
				</items>
			</items>
			<neant>false</neant>
		</mandatElectifDto>
		<participationDirigeantDto>
			<items/>
			<neant>true</neant>
		</participationDirigeantDto>
		<participationFinanciereDto>
			<items/>
			<neant>true</neant>
		</participationFinanciereDto>
		<activCollaborateursDto>
			<items/>
			<neant>false</neant>
		</activCollaborateursDto>
		<observationInteretDto>
			<items/>
			<neant>true</neant>
		</observationInteretDto>
		<general>
			<typeDeclaration>
				<id>DI</id>
				<label>D&#233;claration d'int&#233;r&#234;ts</label>
			</typeDeclaration>
			<mandat>
				<label>Elu local ou membre d&#8217;un &#233;tablissement public de coop&#233;ration intercommunale</label>
			</mandat>
			<qualiteMandat>
				<typeMandat>Membre d&#8217;EPCI</typeMandat>
				<codCategorieMandat>LOC</codCategorieMandat>
				<nomCategorieMandat>Elu local ou membre d&#8217;EPCI</nomCategorieMandat>
				<codTypeMandatFichier>epci</codTypeMandatFichier>
				<labelTypeMandat>Membre d&#8217;EPCI</labelTypeMandat>
				<labelOrgane>EPCI</labelOrgane>
				<codeListeOrgane/>
			</qualiteMandat>
			<organe>
				<codeOrgane/>
				<codeListeOrgane/>
				<nomListeOrgane/>
				<labelOrgane>Communaut&#233; d'Agglom&#233;ration Lens/Li&#233;vin</labelOrgane>
				<labelDeclaration/>
				<organeParent/>
			</organe>
			<qualiteDeclarant/>
			<qualiteDeclarantForPDF>Membre d&#8217;EPCI/Communaut&#233; d'Agglom&#233;ration Lens/Li&#233;vin</qualiteDeclarantForPDF>
			<dateDebutMandat>07/07/2020</dateDebutMandat>
			<dateFinMandat/>
			<dateDernDeclar/>
			<regimeMatrimonial/>
			<regimeMatrimonialComments/>
			<nomSociete/>
			<nomSocieteMere/>
			<chiffreAffaire/>
			<nbLogements/>
			<declarationModificative>false</declarationModificative>
			<declarant>
				<civilite>M.</civilite>
				<nom>LHERBIER</nom>
				<prenom>Alain</prenom>
				<email>
            [Donn&#233;es non publi&#233;es]
        </email>
				<dateNaissance>13/08/1953</dateNaissance>
				<pieceIdentite/>
				<telephoneDec>
            [Donn&#233;es non publi&#233;es]
        </telephoneDec>
				<adresseDec>
					<voie>
            [Donn&#233;es non publi&#233;es]
        </voie>
					<complement>
            [Donn&#233;es non publi&#233;es]
        </complement>
					<codePostal>
            [Donn&#233;es non publi&#233;es]
        </codePostal>
					<ville>
            [Donn&#233;es non publi&#233;es]
        </ville>
					<pays>
            [Donn&#233;es non publi&#233;es]
        </pays>
				</adresseDec>
			</declarant>
		</general>
	</declaration>
	</declarations>
