<declarations><declaration>
		<dateDepot>10/12/2022 13:21:55</dateDepot>
		<uuid>7e681c2c-a70f-4e74-86a2-4dedd2c2aa4c</uuid>
		<origine>ADEL</origine>
		<complete>true</complete>
		<attachedFiles>
			<attachedFiles>
				<fileName>VUE_PDF_DU_RECEPISSE_DU_DEPOT_XML</fileName>
				<serverFileName/>
				<base64EncodedContent/>
			</attachedFiles>
		</attachedFiles>
		<declarationVersion>20171221</declarationVersion>
		<activConsultantDto>
			<items>
				<items>
					<motif>
						<id>CREATION</id>
						<label/>
					</motif>
					<commentaire/>
					<nomEmployeur>OCELLIA</nomEmployeur>
					<description>INTERVENTION COURS</description>
					<dateDebut>03/2022</dateDebut>
					<dateFin>04/2022</dateFin>
					<remuneration>
						<brutNet>Net</brutNet>
						<montant>
							<montant>
								<annee>2022</annee>
								<montant>110</montant>
							</montant>
						</montant>
					</remuneration>
				</items>
				<items>
					<motif>
						<id>CREATION</id>
						<label/>
					</motif>
					<commentaire/>
					<nomEmployeur>OCELLIA</nomEmployeur>
					<description>INTERVENTION COURS</description>
					<dateDebut>04/2021</dateDebut>
					<dateFin>12/2021</dateFin>
					<remuneration>
						<brutNet>Net</brutNet>
						<montant>
							<montant>
								<annee>2021</annee>
								<montant>412</montant>
							</montant>
						</montant>
					</remuneration>
				</items>
				<items>
					<motif>
						<id>CREATION</id>
						<label/>
					</motif>
					<commentaire/>
					<nomEmployeur>CROIX ROUGE</nomEmployeur>
					<description>INTERVENTION COURS</description>
					<dateDebut>03/2021</dateDebut>
					<dateFin>04/2021</dateFin>
					<remuneration>
						<brutNet>Net</brutNet>
						<montant>
							<montant>
								<annee>2021</annee>
								<montant>58</montant>
							</montant>
						</montant>
					</remuneration>
				</items>
			</items>
			<neant>false</neant>
		</activConsultantDto>
		<activProfCinqDerniereDto>
			<items>
				<items>
					<motif>
						<id>CREATION</id>
						<label/>
					</motif>
					<commentaire>EN DISPONIBILITE
        [Donn&#233;es non publi&#233;es]
    </commentaire>
					<conservee>true</conservee>
					<description>PROFESSEUR DES ECOLES</description>
					<employeur>EDUCATION NATIONALE</employeur>
					<remuneration>
						<brutNet>Net</brutNet>
						<montant>
							<montant>
								<annee>2017</annee>
								<montant>0</montant>
							</montant>
							<montant>
								<annee>2018</annee>
								<montant>0</montant>
							</montant>
							<montant>
								<annee>2019</annee>
								<montant>0</montant>
							</montant>
							<montant>
								<annee>2020</annee>
								<montant>0</montant>
							</montant>
							<montant>
								<annee>2021</annee>
								<montant>0</montant>
							</montant>
							<montant>
								<annee>2022</annee>
								<montant>0</montant>
							</montant>
						</montant>
					</remuneration>
					<dateDebut>01/2017</dateDebut>
					<dateFin>07/2022</dateFin>
				</items>
			</items>
			<neant>false</neant>
		</activProfCinqDerniereDto>
		<activProfConjointDto>
			<items>
				<items>
					<motif>
						<id>CREATION</id>
						<label/>
					</motif>
					<commentaire/>
					<nomConjoint>
            [Donn&#233;es non publi&#233;es]
        </nomConjoint>
					<employeurConjoint>HUGUES CONSEIL</employeurConjoint>
					<activiteProf>Conseil et assistance au repreneur
        [Donn&#233;es non publi&#233;es]
    </activiteProf>
				</items>
			</items>
			<neant>false</neant>
		</activProfConjointDto>
		<fonctionBenevoleDto>
			<items/>
			<neant>true</neant>
		</fonctionBenevoleDto>
		<mandatElectifDto>
			<items/>
			<neant>true</neant>
		</mandatElectifDto>
		<participationDirigeantDto>
			<items>
				<items>
					<motif>
						<id>CREATION</id>
						<label/>
					</motif>
					<commentaire/>
					<nomSociete>RESEAU LOISIRS PLURIEL</nomSociete>
					<activite>PRESIDENTE</activite>
					<remuneration>
						<brutNet>Net</brutNet>
						<montant>
							<montant>
								<annee>2018</annee>
								<montant>0</montant>
							</montant>
							<montant>
								<annee>2019</annee>
								<montant>0</montant>
							</montant>
							<montant>
								<annee>2020</annee>
								<montant>0</montant>
							</montant>
							<montant>
								<annee>2021</annee>
								<montant>0</montant>
							</montant>
							<montant>
								<annee>2022</annee>
								<montant>0</montant>
							</montant>
						</montant>
					</remuneration>
					<dateDebut>10/2018</dateDebut>
					<dateFin>06/2022</dateFin>
				</items>
				<items>
					<motif>
						<id>CREATION</id>
						<label/>
					</motif>
					<commentaire/>
					<nomSociete>LOISIRS PLURIEL PORTE DES ALPES</nomSociete>
					<activite>PRESIDENTE FONDATRICE</activite>
					<remuneration>
						<brutNet>Net</brutNet>
						<montant>
							<montant>
								<annee>2016</annee>
								<montant>0</montant>
							</montant>
							<montant>
								<annee>2017</annee>
								<montant>0</montant>
							</montant>
							<montant>
								<annee>2018</annee>
								<montant>0</montant>
							</montant>
							<montant>
								<annee>2019</annee>
								<montant>0</montant>
							</montant>
							<montant>
								<annee>2020</annee>
								<montant>0</montant>
							</montant>
							<montant>
								<annee>2021</annee>
								<montant>0</montant>
							</montant>
						</montant>
					</remuneration>
					<dateDebut>01/2016</dateDebut>
					<dateFin>06/2021</dateFin>
				</items>
			</items>
			<neant>false</neant>
		</participationDirigeantDto>
		<participationFinanciereDto>
			<items>
				<items>
					<motif>
						<id>CREATION</id>
						<label/>
					</motif>
					<commentaire>
        [Donn&#233;es non publi&#233;es]
    </commentaire>
					<nomSociete>SCI 
        [Donn&#233;es non publi&#233;es]
    </nomSociete>
					<evaluation>367896</evaluation>
					<remuneration>0</remuneration>
					<capitalDetenu>50</capitalDetenu>
					<nombreParts>5</nombreParts>
					<actiConseil>Non</actiConseil>
				</items>
			</items>
			<neant>false</neant>
		</participationFinanciereDto>
		<activCollaborateursDto>
			<items>
				<items>
					<motif>
						<id>CREATION</id>
						<label/>
					</motif>
					<commentaire/>
					<nom>QUILES ROBIN</nom>
					<employeur/>
					<descriptionActivite/>
				</items>
				<items>
					<motif>
						<id>CREATION</id>
						<label/>
					</motif>
					<commentaire/>
					<nom>FERRUCCI Loick</nom>
					<employeur>Mairie de SEYSSINS</employeur>
					<descriptionActivite>Conseiller municipal d&#233;l&#233;gu&#233; aux sports</descriptionActivite>
				</items>
				<items>
					<motif>
						<id>CREATION</id>
						<label/>
					</motif>
					<commentaire/>
					<nom>AUGUERES Marie Elise</nom>
					<employeur/>
					<descriptionActivite/>
				</items>
			</items>
			<neant>false</neant>
		</activCollaborateursDto>
		<observationInteretDto>
			<neant>true</neant>
		</observationInteretDto>
		<general>
			<typeDeclaration>
				<id>DIA</id>
				<label>D&#233;claration d'int&#233;r&#234;ts et d'activit&#233;s modificative</label>
			</typeDeclaration>
			<mandat>
				<label>D&#233;put&#233; ou s&#233;nateur</label>
			</mandat>
			<qualiteMandat>
				<typeMandat>D&#233;put&#233;</typeMandat>
				<codCategorieMandat>PAR</codCategorieMandat>
				<nomCategorieMandat>D&#233;put&#233; ou s&#233;nateur</nomCategorieMandat>
				<codTypeMandatFichier>depute</codTypeMandatFichier>
				<labelTypeMandat>D&#233;put&#233;</labelTypeMandat>
				<labelOrgane>D&#233;partement d'&#233;lection</labelOrgane>
				<codeListeOrgane>ZEP</codeListeOrgane>
			</qualiteMandat>
			<organe>
				<codeOrgane>38</codeOrgane>
				<codeListeOrgane>ZEP</codeListeOrgane>
				<nomListeOrgane>Zones d'&#233;lection des parlementaires</nomListeOrgane>
				<labelOrgane>Is&#232;re(38)</labelOrgane>
				<labelDeclaration/>
				<organeParent/>
			</organe>
			<qualiteDeclarant/>
			<qualiteDeclarantForPDF>D&#233;put&#233;/Is&#232;re(38)</qualiteDeclarantForPDF>
			<dateDebutMandat>23/07/2022</dateDebutMandat>
			<dateFinMandat/>
			<dateDernDeclar/>
			<regimeMatrimonial/>
			<regimeMatrimonialComments/>
			<nomSociete/>
			<nomSocieteMere/>
			<chiffreAffaire/>
			<nbLogements/>
			<declarationModificative>true</declarationModificative>
			<etablissement/>
			<declarant>
				<civilite>Mme</civilite>
				<nom>HUGUES</nom>
				<prenom>Servane</prenom>
				<email>
            [Donn&#233;es non publi&#233;es]
        </email>
				<dateNaissance>28/06/1976</dateNaissance>
				<pieceIdentite/>
				<telephoneDec>
            [Donn&#233;es non publi&#233;es]
        </telephoneDec>
				<adresseDec>
					<voie>
            [Donn&#233;es non publi&#233;es]
        </voie>
					<complement>
            [Donn&#233;es non publi&#233;es]
        </complement>
					<codePostal>
            [Donn&#233;es non publi&#233;es]
        </codePostal>
					<ville>
            [Donn&#233;es non publi&#233;es]
        </ville>
					<pays>
            [Donn&#233;es non publi&#233;es]
        </pays>
				</adresseDec>
			</declarant>
		</general>
	</declaration>
	</declarations>
