<declarations><declaration>
		<dateDepot>26/08/2021 18:25:20</dateDepot>
		<uuid>8379c1e3-4e0d-44a9-bdf0-256263d54a9a</uuid>
		<origine>ADEL</origine>
		<complete>true</complete>
		<attachedFiles>
			<attachedFiles>
				<fileName>VUE_PDF_DU_RECEPISSE_DU_DEPOT_XML</fileName>
				<serverFileName/>
				<base64EncodedContent/>
			</attachedFiles>
		</attachedFiles>
		<declarationVersion>20171221</declarationVersion>
		<activConsultantDto>
			<items/>
			<neant>true</neant>
		</activConsultantDto>
		<activProfCinqDerniereDto>
			<items/>
			<neant>true</neant>
		</activProfCinqDerniereDto>
		<activProfConjointDto>
			<items>
				<items>
					<motif>
						<id>CREATION</id>
						<label/>
					</motif>
					<commentaire>
        [Donn&#233;es non publi&#233;es]
    </commentaire>
					<nomConjoint>
            [Donn&#233;es non publi&#233;es]
        </nomConjoint>
					<employeurConjoint>retrait&#233;e &#233;ducation nationale</employeurConjoint>
					<activiteProf>Retrait&#233;e</activiteProf>
				</items>
			</items>
			<neant>false</neant>
		</activProfConjointDto>
		<fonctionBenevoleDto>
			<items/>
			<neant>true</neant>
		</fonctionBenevoleDto>
		<mandatElectifDto>
			<items/>
			<neant>true</neant>
		</mandatElectifDto>
		<participationDirigeantDto>
			<items>
				<items>
					<motif>
						<id>CREATION</id>
						<label/>
					</motif>
					<commentaire>Pr&#233;sidence de l'association exerc&#233;e &#224; titre b&#233;n&#233;vole depuis 1999.</commentaire>
					<nomSociete>Festival film d'histoire de Pessac</nomSociete>
					<activite>pr&#233;sident</activite>
					<remuneration>
						<brutNet>Net</brutNet>
						<montant>
							<montant>
								<annee>2015</annee>
								<montant>0</montant>
							</montant>
							<montant>
								<annee>2016</annee>
								<montant>0</montant>
							</montant>
							<montant>
								<annee>2017</annee>
								<montant>0</montant>
							</montant>
							<montant>
								<annee>2018</annee>
								<montant>0</montant>
							</montant>
							<montant>
								<annee>2019</annee>
								<montant>0</montant>
							</montant>
							<montant>
								<annee>2020</annee>
								<montant>0</montant>
							</montant>
							<montant>
								<annee>2021</annee>
								<montant>0</montant>
							</montant>
						</montant>
					</remuneration>
					<dateDebut>01/2015</dateDebut>
					<dateFin>12/2021</dateFin>
				</items>
				<items>
					<motif>
						<id>CREATION</id>
						<label/>
					</motif>
					<commentaire>Activit&#233; exerc&#233;e &#224; titre b&#233;n&#233;vole depuis mon &#233;lection le 19 mars 2018</commentaire>
					<nomSociete>Sem route des lasers</nomSociete>
					<activite>pr&#233;sident</activite>
					<remuneration>
						<brutNet>Net</brutNet>
						<montant>
							<montant>
								<annee>2018</annee>
								<montant>0</montant>
							</montant>
							<montant>
								<annee>2019</annee>
								<montant>0</montant>
							</montant>
							<montant>
								<annee>2020</annee>
								<montant>0</montant>
							</montant>
							<montant>
								<annee>2021</annee>
								<montant>0</montant>
							</montant>
						</montant>
					</remuneration>
					<dateDebut>03/2018</dateDebut>
					<dateFin>12/2021</dateFin>
				</items>
				<items>
					<motif>
						<id>CREATION</id>
						<label/>
					</motif>
					<commentaire>La pr&#233;sidence du Conseil de surveillance de l'agence de d&#233;veloppement industriel est exerc&#233;e &#224; titre b&#233;n&#233;vole depuis mon &#233;lection le 20 octobre 2018</commentaire>
					<nomSociete>ADI</nomSociete>
					<activite>pr&#233;sident</activite>
					<remuneration>
						<brutNet>Net</brutNet>
						<montant>
							<montant>
								<annee>2018</annee>
								<montant>0</montant>
							</montant>
							<montant>
								<annee>2019</annee>
								<montant>0</montant>
							</montant>
							<montant>
								<annee>2020</annee>
								<montant>0</montant>
							</montant>
							<montant>
								<annee>2021</annee>
								<montant>0</montant>
							</montant>
						</montant>
					</remuneration>
					<dateDebut>10/2018</dateDebut>
					<dateFin>12/2021</dateFin>
				</items>
			</items>
			<neant>false</neant>
		</participationDirigeantDto>
		<participationFinanciereDto>
			<items>
				<items>
					<motif>
						<id>CREATION</id>
						<label/>
					</motif>
					<commentaire>J'ai ouvert un PEA (plan d'&#233;pargne en actions) le 24 d&#233;cembre 1992 et il me semble que je d&#233;tiens les 33 premiers titres de la soci&#233;t&#233; Safran depuis cette &#233;poque. Par la suite, j'ai achet&#233; 100 nouveaux titres 
        [Donn&#233;es non publi&#233;es]
     
        [Donn&#233;es non publi&#233;es]
    </commentaire>
					<nomSociete>Safran</nomSociete>
					<evaluation>15421</evaluation>
					<remuneration>0</remuneration>
					<capitalDetenu>0</capitalDetenu>
					<nombreParts>133</nombreParts>
				</items>
				<items>
					<motif>
						<id>CREATION</id>
						<label/>
					</motif>
					<commentaire>
        [Donn&#233;es non publi&#233;es]
    </commentaire>
					<nomSociete>Soci&#233;t&#233; g&#233;n&#233;rale</nomSociete>
					<evaluation>221</evaluation>
					<remuneration>0</remuneration>
					<capitalDetenu>0</capitalDetenu>
					<nombreParts>13</nombreParts>
				</items>
				<items>
					<motif>
						<id>CREATION</id>
						<label/>
					</motif>
					<commentaire>Ces titres font partie de mon &#233;pargne salariale (PEGT et PEG-A).</commentaire>
					<nomSociete>Total</nomSociete>
					<evaluation>153407</evaluation>
					<remuneration>0</remuneration>
					<capitalDetenu>0</capitalDetenu>
					<nombreParts>4376</nombreParts>
				</items>
				<items>
					<motif>
						<id>CREATION</id>
						<label/>
					</motif>
					<commentaire>Titres &#233;pargne salariale (PEGT, PEG-A et Ex ELF Privatisation)</commentaire>
					<nomSociete>Arkema</nomSociete>
					<evaluation>7565</evaluation>
					<remuneration>&#224;</remuneration>
					<capitalDetenu>0</capitalDetenu>
					<nombreParts>83</nombreParts>
				</items>
				<items>
					<motif>
						<id>CREATION</id>
						<label/>
					</motif>
					<commentaire>Titres inscrits sur le PEGT de mon &#233;pargne salariale.</commentaire>
					<nomSociete>Sanofi</nomSociete>
					<evaluation>88974</evaluation>
					<remuneration>0</remuneration>
					<capitalDetenu>0</capitalDetenu>
					<nombreParts>1200</nombreParts>
				</items>
			</items>
			<neant>false</neant>
		</participationFinanciereDto>
		<activCollaborateursDto>
			<items/>
			<neant>false</neant>
		</activCollaborateursDto>
		<observationInteretDto>
			<items/>
			<neant>true</neant>
		</observationInteretDto>
		<general>
			<typeDeclaration>
				<id>DI</id>
				<label>D&#233;claration d'int&#233;r&#234;ts</label>
			</typeDeclaration>
			<mandat>
				<label>Elu local ou membre d&#8217;un &#233;tablissement public de coop&#233;ration intercommunale</label>
			</mandat>
			<qualiteMandat>
				<typeMandat>Elu r&#233;gional</typeMandat>
				<codCategorieMandat>LOC</codCategorieMandat>
				<nomCategorieMandat>Elu local ou membre d&#8217;EPCI</nomCategorieMandat>
				<codTypeMandatFichier>cr</codTypeMandatFichier>
				<labelTypeMandat>Elu r&#233;gional</labelTypeMandat>
				<labelOrgane>R&#233;gion</labelOrgane>
				<codeListeOrgane>REG</codeListeOrgane>
			</qualiteMandat>
			<organe>
				<codeOrgane>75</codeOrgane>
				<codeListeOrgane>REG</codeListeOrgane>
				<nomListeOrgane>R&#233;gions</nomListeOrgane>
				<labelOrgane>Nouvelle-Aquitaine (75)</labelOrgane>
				<labelDeclaration/>
				<organeParent/>
			</organe>
			<qualiteDeclarant/>
			<qualiteDeclarantForPDF>Elu r&#233;gional/Nouvelle-Aquitaine (75)</qualiteDeclarantForPDF>
			<dateDebutMandat>02/07/2021</dateDebutMandat>
			<dateFinMandat/>
			<dateDernDeclar/>
			<regimeMatrimonial/>
			<regimeMatrimonialComments/>
			<nomSociete/>
			<nomSocieteMere/>
			<chiffreAffaire/>
			<nbLogements/>
			<declarationModificative>false</declarationModificative>
			<declarant>
				<civilite>M.</civilite>
				<nom>ROUSSET</nom>
				<prenom>ALAIN PIERRE MARIE</prenom>
				<email>
            [Donn&#233;es non publi&#233;es]
        </email>
				<dateNaissance>16/02/1951</dateNaissance>
				<pieceIdentite/>
				<telephoneDec>
            [Donn&#233;es non publi&#233;es]
        </telephoneDec>
				<adresseDec>
					<voie>
            [Donn&#233;es non publi&#233;es]
        </voie>
					<complement>
            [Donn&#233;es non publi&#233;es]
        </complement>
					<codePostal>
            [Donn&#233;es non publi&#233;es]
        </codePostal>
					<ville>
            [Donn&#233;es non publi&#233;es]
        </ville>
					<pays>
            [Donn&#233;es non publi&#233;es]
        </pays>
				</adresseDec>
			</declarant>
		</general>
	</declaration>
	</declarations>
